cachingutils/__init__.py
cachingutils/cache.py
cachingutils/deco.py
cachingutils-1.0.7.dist-info/LICENSE
cachingutils-1.0.7.dist-info/WHEEL
cachingutils-1.0.7.dist-info/METADATA
cachingutils-1.0.7.dist-info/RECORD
