Metadata-Version: 2.1
Name: cachingutils
Version: 1.0.7
Summary: Utilities to make caching data easier
Home-page: https://github.com/vcokltfre/cachingutils
License: MIT
Author: vcokltfre
Author-email: vcokltfre@gmail.com
Requires-Python: >=3.9,<4.0
Classifier: License :: OSI Approved :: MIT License
Classifier: Programming Language :: Python :: 3
Classifier: Programming Language :: Python :: 3.10
Classifier: Programming Language :: Python :: 3.9
Requires-Dist: lru-dict (>=1.1.7,<2.0.0)
Project-URL: Repository, https://github.com/vcokltfre/cachingutils
